mzqc/MZQCFile.py
mzqc/SemanticCheck.py
mzqc/SyntaxCheck.py
mzqc/__init__.py
mzqcaccessories/__init__.py
mzqcaccessories/validator_core.py
mzqcaccessories/filehandling/__init__.py
mzqcaccessories/filehandling/mzqc_fileinfo.py
mzqcaccessories/filehandling/mzqc_filemerger.py
mzqcaccessories/filehandling/mzqc_fixdescriptions.py
mzqcaccessories/offlinevalidator/__init__.py
mzqcaccessories/offlinevalidator/mzqc_offline_validator.py
pymzqc-1.0.1.dist-info/licenses/LICENSE
pymzqc-1.0.1.dist-info/METADATA
pymzqc-1.0.1.dist-info/WHEEL
pymzqc-1.0.1.dist-info/entry_points.txt
pymzqc-1.0.1.dist-info/top_level.txt
pymzqc-1.0.1.dist-info/RECORD
