Metadata-Version: 2.4
Name: pymzqc
Version: 1.0.1
Summary: Python library for the PSI-mzQC quality control file format.
Home-page: https://github.com/MS-Quality-hub/pymzqc
Author: Mathias Walzer
Author-email: walzer@ebi.ack.uk
Requires-Python: >=3.8
License-File: LICENSE
Requires-Dist: jsonschema>=3.2.0
Requires-Dist: strict-rfc3339
Requires-Dist: rfc3339-validator
Requires-Dist: numpy
Requires-Dist: pandas>=1.1.5
Requires-Dist: pronto
Requires-Dist: requests>=2.27.1
Requires-Dist: click
Dynamic: author
Dynamic: author-email
Dynamic: description
Dynamic: description-content-type
Dynamic: home-page
Dynamic: license-file
Dynamic: requires-dist
Dynamic: requires-python
Dynamic: summary
